{"odds_map": {"New York Mets@Cincinnati Reds": {"moneyline": {}, "total": {"line": "9.0", "over": -110, "under": -110}, "runline": {}}, "Kansas City Royals@Washington Nationals": {"moneyline": {}, "total": {"line": "10.5", "over": -110, "under": -110}, "runline": {}}, "Miami Marlins@Philadelphia Phillies": {"moneyline": {}, "total": {"line": "9.0", "over": -110, "under": -110}, "runline": {}}, "Detroit Tigers@Houston Astros": {"moneyline": {}, "total": {"line": "8.5", "over": -110, "under": -110}, "runline": {}}, "San Diego Padres@St. Louis Cardinals": {"moneyline": {}, "total": {"line": "10.5", "over": -110, "under": -110}, "runline": {}}, "Tampa Bay Rays@Los Angeles Dodgers": {"moneyline": {}, "total": {"line": "7.0", "over": -110, "under": -110}, "runline": {}}, "Los Angeles Angels@Arizona Diamondbacks": {"moneyline": {}, "total": {"line": "9.5", "over": -110, "under": -110}, "runline": {}}, "Toronto Blue Jays@Boston Red Sox": {"moneyline": {}, "total": {"line": "9.5", "over": -110, "under": -110}, "runline": {}}, "Chicago White Sox@New York Yankees": {"moneyline": {}, "total": {"line": "8.5", "over": -110, "under": -110}, "runline": {}}, "San Francisco Giants@Atlanta Braves": {"moneyline": {}, "total": {"line": "9.0", "over": -110, "under": -110}, "runline": {}}, "Cleveland Guardians@Milwaukee Brewers": {"moneyline": {}, "total": {"line": "7.5", "over": -110, "under": -110}, "runline": {}}, "Colorado Rockies@Chicago Cubs": {"moneyline": {}, "total": {"line": "10.0", "over": -110, "under": -110}, "runline": {}}, "Baltimore Orioles@Seattle Mariners": {"moneyline": {}, "total": {"line": "7.5", "over": -110, "under": -110}, "runline": {}}, "Pittsburgh Pirates@Athletics": {"moneyline": {}, "total": {"line": "10.0", "over": -110, "under": -110}, "runline": {}}}, "event_ids": {"San Francisco Giants@Atlanta Braves": "401815793", "New York Mets@Cincinnati Reds": "401815792", "Kansas City Royals@Washington Nationals": "401815790", "Miami Marlins@Philadelphia Phillies": "401815791", "Detroit Tigers@Houston Astros": "401815797", "San Diego Padres@St. Louis Cardinals": "401815798", "Tampa Bay Rays@Los Angeles Dodgers": "401815802", "Los Angeles Angels@Arizona Diamondbacks": "401815799", "Toronto Blue Jays@Boston Red Sox": "401815794", "Chicago White Sox@New York Yankees": "401815789", "Cleveland Guardians@Milwaukee Brewers": "401815795", "Colorado Rockies@Chicago Cubs": "401815796", "Baltimore Orioles@Seattle Mariners": "401815800", "Pittsburgh Pirates@Athletics": "401815801"}}