{"odds_map": {"Boston Red Sox@Tampa Bay Rays": {"moneyline": {}, "total": {"line": "7.5", "over": -110, "under": -110}, "runline": {}}, "New York Yankees@Cleveland Guardians": {"moneyline": {}, "total": {"line": "8.0", "over": -110, "under": -110}, "runline": {}}, "Washington Nationals@San Francisco Giants": {"moneyline": {}, "total": {"line": "8.0", "over": -110, "under": -110}, "runline": {}}, "Cincinnati Reds@San Diego Padres": {"moneyline": {}, "total": {"line": "8.0", "over": -110, "under": -110}, "runline": {}}, "Seattle Mariners@Baltimore Orioles": {"moneyline": {}, "total": {"line": "9.0", "over": -110, "under": -110}, "runline": {}}, "Arizona Diamondbacks@Miami Marlins": {"moneyline": {}, "total": {"line": "8.5", "over": -110, "under": -110}, "runline": {}}, "Los Angeles Dodgers@Pittsburgh Pirates": {"moneyline": {}, "total": {"line": "8.5", "over": -110, "under": -110}, "runline": {}}, "Minnesota Twins@Detroit Tigers": {"moneyline": {}, "total": {"line": "9.0", "over": -110, "under": -110}, "runline": {}}, "Philadelphia Phillies@Toronto Blue Jays": {"moneyline": {}, "total": {"line": "8.5", "over": -110, "under": -110}, "runline": {}}, "St. Louis Cardinals@New York Mets": {"moneyline": {}, "total": {"line": "8.5", "over": -110, "under": -110}, "runline": {}}, "Atlanta Braves@Chicago White Sox": {"moneyline": {}, "total": {"line": "7.5", "over": -110, "under": -110}, "runline": {}}, "Texas Rangers@Kansas City Royals": {"moneyline": {}, "total": {"line": "10.0", "over": -110, "under": -110}, "runline": {}}, "Chicago Cubs@Colorado Rockies": {"moneyline": {}, "total": {"line": "12.5", "over": -110, "under": -110}, "runline": {}}, "Milwaukee Brewers@Athletics": {"moneyline": {}, "total": {"line": "14.5", "over": -110, "under": -110}, "runline": {}}, "Houston Astros@Los Angeles Angels": {"moneyline": {}, "total": {"line": "9.0", "over": -110, "under": -110}, "runline": {}}}, "event_ids": {"Boston Red Sox@Tampa Bay Rays": "401815697", "New York Yankees@Cleveland Guardians": "401815700", "Washington Nationals@San Francisco Giants": "401815710", "Cincinnati Reds@San Diego Padres": "401815707", "Seattle Mariners@Baltimore Orioles": "401815702", "Arizona Diamondbacks@Miami Marlins": "401815696", "Los Angeles Dodgers@Pittsburgh Pirates": "401815698", "Minnesota Twins@Detroit Tigers": "401815699", "Philadelphia Phillies@Toronto Blue Jays": "401815701", "St. Louis Cardinals@New York Mets": "401815703", "Atlanta Braves@Chicago White Sox": "401815704", "Texas Rangers@Kansas City Royals": "401815705", "Chicago Cubs@Colorado Rockies": "401815706", "Milwaukee Brewers@Athletics": "401815709", "Houston Astros@Los Angeles Angels": "401815708"}}